jsontoxl/__init__.py
jsontoxl/converter.py
JsonXL-1.0.0.dist-info/METADATA
JsonXL-1.0.0.dist-info/WHEEL
JsonXL-1.0.0.dist-info/entry_points.txt
JsonXL-1.0.0.dist-info/top_level.txt
JsonXL-1.0.0.dist-info/RECORD
